datafuzz/__init__.py
datafuzz/__main__.py
datafuzz/__version__.py
datafuzz/cli.py
datafuzz/dataset.py
datafuzz/duplicator.py
datafuzz/fuzz.py
datafuzz/noise.py
datafuzz/settings.py
datafuzz/strategy.py
datafuzz/generators/__init__.py
datafuzz/generators/core.py
datafuzz/output/__init__.py
datafuzz/output/core.py
datafuzz/output/helpers.py
datafuzz/parsers/__init__.py
datafuzz/parsers/core.py
datafuzz/parsers/helpers.py
datafuzz/utils/__init__.py
datafuzz/utils/fuzz_helpers.py
datafuzz/utils/noise_helpers.py
tests/__init__.py
tests/test_cli.py
tests/test_dataset.py
tests/test_duplicator.py
tests/test_fuzz.py
tests/test_fuzz_helpers.py
tests/test_noise.py
tests/test_noise_helpers.py
tests/data/bad_datetime_schema.yaml
tests/data/bad_json.json
tests/data/bad_yaml.yaml
tests/data/incomplete_schema.yaml
tests/data/test_csv.csv
tests/data/test_db.db
tests/data/test_json.json
tests/data/test_output.db-shm
tests/data/test_output.db-wal
tests/generators/__init__.py
tests/generators/test_generator.py
tests/output/__init__.py
tests/output/test_sql.py
tests/parsers/__init__.py
tests/parsers/test_helpers.py
tests/parsers/test_parsers.py
datafuzz-0.1.2.dist-info/AUTHORS.rst
datafuzz-0.1.2.dist-info/LICENSE
datafuzz-0.1.2.dist-info/METADATA
datafuzz-0.1.2.dist-info/WHEEL
datafuzz-0.1.2.dist-info/entry_points.txt
datafuzz-0.1.2.dist-info/top_level.txt
datafuzz-0.1.2.dist-info/RECORD
