Metadata-Version: 2.1
Name: datafuzz
Version: 0.1.2
Summary: A data-science library built for testing cleaning, schema validation and model robustness. It messes up your data so you can test your data engineering and data science code (before it breaks in production).
Home-page: https://github.com/kjam/datafuzz
Author: Katharine Jarmul
Author-email: katharine@kjamistan.com
License: BSD license
Keywords: datafuzz
Classifier: Development Status :: 2 - Pre-Alpha
Classifier: Intended Audience :: Developers
Classifier: License :: OSI Approved :: BSD License
Classifier: Natural Language :: English
Classifier: Programming Language :: Python :: 3
Classifier: Programming Language :: Python :: 3.8
Classifier: Programming Language :: Python :: 3.9
Classifier: Programming Language :: Python :: 3.10
License-File: LICENSE
License-File: AUTHORS.rst
Requires-Dist: faker
Requires-Dist: dataset
Requires-Dist: pyyaml
